secureaws/__init__.py
secureaws/__main__.py
secureaws/checkaws.py
secureaws/common.py
secureaws/rsautil.py
secureaws/secureaws.py
secureaws/setupaws.py
secureaws-19.12.5.dist-info/LICENCE
secureaws-19.12.5.dist-info/METADATA
secureaws-19.12.5.dist-info/WHEEL
secureaws-19.12.5.dist-info/entry_points.txt
secureaws-19.12.5.dist-info/top_level.txt
secureaws-19.12.5.dist-info/RECORD
