Metadata-Version: 2.1
Name: secureaws
Version: 19.12.5
Summary: An application to scan if basic security services are enabled on your AWS account and help you setup the same.
Home-page: https://github.com/paliwalvimal/secure-aws
Author: Vimal Paliwal
Author-email: hello@vimalpaliwal.com
License: MIT
Keywords: aws secure security cloudtrail config encryption
Platform: UNKNOWN
Classifier: Programming Language :: Python :: 3
Classifier: License :: OSI Approved :: MIT License
Classifier: Operating System :: OS Independent
Requires-Python: >=3.6
Requires-Dist: click
Requires-Dist: Pillow
Requires-Dist: pycryptodomex
Requires-Dist: boto3
